[{"date":"20090821","ticker":"DHI","open":"12.42","high":"12.89","low":"12.385","close":"12.66","volume":"75726"},{"date":"20090824","ticker":"DHI","open":"12.85","high":"13","low":"12.61","close":"12.67","volume":"71231"},{"date":"20090825","ticker":"DHI","open":"12.81","high":"13.35","low":"12.81","close":"13.05","volume":"62617"},{"date":"20090826","ticker":"DHI","open":"13.22","high":"13.9","low":"13.03","close":"13.79","volume":"166528"},{"date":"20090827","ticker":"DHI","open":"13.63","high":"13.71","low":"12.91","close":"13.53","volume":"91564"},{"date":"20090828","ticker":"DHI","open":"13.71","high":"13.88","low":"13.52","close":"13.72","volume":"61900"},{"date":"20090831","ticker":"DHI","open":"13.51","high":"13.57","low":"13.22","close":"13.41","volume":"47837"},{"date":"20090901","ticker":"DHI","open":"13.31","high":"13.86","low":"12.85","close":"12.91","volume":"72013"},{"date":"20090902","ticker":"DHI","open":"12.6","high":"12.74","low":"12.08","close":"12.13","volume":"105986"},{"date":"20090903","ticker":"DHI","open":"12.15","high":"12.3","low":"11.78","close":"12.26","volume":"84431"},{"date":"20090904","ticker":"DHI","open":"12.25","high":"12.54","low":"12.06","close":"12.45","volume":"32137"},{"date":"20090909","ticker":"DHI","open":"12.96","high":"13.1","low":"12.66","close":"12.98","volume":"66315"},{"date":"20090910","ticker":"DHI","open":"13.08","high":"13.16","low":"12.74","close":"13.12","volume":"32592"},{"date":"20090911","ticker":"DHI","open":"13.14","high":"13.31","low":"12.51","close":"12.69","volume":"68172"},{"date":"20090914","ticker":"DHI","open":"12.6","high":"12.8074","low":"12.429","close":"12.54","volume":"71402"},{"date":"20090915","ticker":"DHI","open":"12.57","high":"13.05","low":"12.49","close":"12.97","volume":"66419"},{"date":"20090916","ticker":"DHI","open":"13.15","high":"13.73","low":"13.07","close":"13.63","volume":"130045"},{"date":"20090917","ticker":"DHI","open":"13.77","high":"13.79","low":"13.01","close":"13.19","volume":"67312"},{"date":"20090918","ticker":"DHI","open":"13.36","high":"13.675","low":"13.1","close":"13.25","volume":"77260"},{"date":"20090921","ticker":"DHI","open":"13.13","high":"13.29","low":"12.75","close":"13.04","volume":"47986"},{"date":"20090922","ticker":"DHI","open":"13.18","high":"13.37","low":"12.86","close":"12.9","volume":"64575"},{"date":"20090923","ticker":"DHI","open":"12.91","high":"12.91","low":"12.43","close":"12.45","volume":"61481"},{"date":"20090924","ticker":"DHI","open":"12.67","high":"12.85","low":"11.72","close":"11.93","volume":"110063"},{"date":"20090925","ticker":"DHI","open":"11.86","high":"12.03","low":"11.49","close":"11.57","volume":"72664"},{"date":"20090928","ticker":"DHI","open":"11.68","high":"11.84","low":"11.51","close":"11.77","volume":"32331"},{"date":"20090929","ticker":"DHI","open":"11.99","high":"12.13","low":"11.78","close":"11.87","volume":"49144"},{"date":"20090930","ticker":"DHI","open":"11.86","high":"11.92","low":"11.3","close":"11.41","volume":"86783"},{"date":"20091001","ticker":"DHI","open":"11.25","high":"11.3","low":"10.95","close":"11.01","volume":"107520"},{"date":"20091002","ticker":"DHI","open":"10.83","high":"10.91","low":"10.46","close":"10.53","volume":"112782"},{"date":"20091005","ticker":"DHI","open":"10.67","high":"10.86","low":"10.56","close":"10.79","volume":"65584"},{"date":"20091006","ticker":"DHI","open":"10.98","high":"11.32","low":"10.9","close":"10.95","volume":"85082"},{"date":"20091007","ticker":"DHI","open":"10.97","high":"11.08","low":"10.5","close":"10.69","volume":"85038"},{"date":"20091008","ticker":"DHI","open":"10.86","high":"11.7","low":"10.86","close":"11.54","volume":"121930"},{"date":"20091009","ticker":"DHI","open":"11.5","high":"12.09","low":"11.34","close":"11.7","volume":"84598"},{"date":"20091012","ticker":"DHI","open":"11.72","high":"11.83","low":"11.54","close":"11.57","volume":"52165"},{"date":"20091013","ticker":"DHI","open":"11.56","high":"12.12","low":"11.47","close":"11.79","volume":"74271"},{"date":"20091014","ticker":"DHI","open":"12.03","high":"12.36","low":"12.03","close":"12.26","volume":"71073"},{"date":"20091015","ticker":"DHI","open":"12.18","high":"12.52","low":"12.06","close":"12.43","volume":"69716"},{"date":"20091016","ticker":"DHI","open":"12.27","high":"12.37","low":"12.085","close":"12.2","volume":"58702"},{"date":"20091019","ticker":"DHI","open":"12.21","high":"12.42","low":"12.06","close":"12.25","volume":"83453"},{"date":"20091020","ticker":"DHI","open":"12.03","high":"12.31","low":"11.9","close":"12.09","volume":"70760"},{"date":"20091021","ticker":"DHI","open":"12.15","high":"12.61","low":"12.12","close":"12.17","volume":"84893"},{"date":"20091022","ticker":"DHI","open":"12.08","high":"13","low":"11.93","close":"12.7","volume":"127588"},{"date":"20091023","ticker":"DHI","open":"12.84","high":"12.99","low":"12.11","close":"12.42","volume":"113196"},{"date":"20091026","ticker":"DHI","open":"12.46","high":"12.58","low":"11.84","close":"11.93","volume":"70812"},{"date":"20091027","ticker":"DHI","open":"12.02","high":"12.19","low":"11.67","close":"11.81","volume":"74303"},{"date":"20091028","ticker":"DHI","open":"11.66","high":"11.75","low":"11.1","close":"11.12","volume":"113321"},{"date":"20091105","ticker":"DHI","open":"11.68","high":"12.24","low":"11.52","close":"11.83","volume":"87860"},{"date":"20091106","ticker":"DHI","open":"11.79","high":"12.12","low":"11.63","close":"12.03","volume":"67086"},{"date":"20091109","ticker":"DHI","open":"12.17","high":"12.24","low":"11.83","close":"12.13","volume":"83964"},{"date":"20091110","ticker":"DHI","open":"12.09","high":"12.25","low":"11.53","close":"11.69","volume":"75725"},{"date":"20091111","ticker":"DHI","open":"12.06","high":"12.45","low":"11.96","close":"12.36","volume":"81952"},{"date":"20091112","ticker":"DHI","open":"12.33","high":"12.33","low":"11.8","close":"11.86","volume":"72916"},{"date":"20091113","ticker":"DHI","open":"11.87","high":"12.28","low":"11.85","close":"11.94","volume":"78060"},{"date":"20091116","ticker":"DHI","open":"11.98","high":"12.54","low":"11.98","close":"12.31","volume":"78926"},{"date":"20091117","ticker":"DHI","open":"12.17","high":"12.37","low":"11.91","close":"12.14","volume":"73562"},{"date":"20091118","ticker":"DHI","open":"11.94","high":"12.49","low":"11.94","close":"12.37","volume":"64005"},{"date":"20091119","ticker":"DHI","open":"12.25","high":"12.305","low":"11.925","close":"12.25","volume":"102718"},{"date":"20091120","ticker":"DHI","open":"11.47","high":"11.63","low":"10.24","close":"10.37","volume":"358884"},{"date":"20091123","ticker":"DHI","open":"10.63","high":"10.909","low":"10.46","close":"10.66","volume":"171183"},{"date":"20091124","ticker":"DHI","open":"10.79","high":"10.85","low":"10.385","close":"10.58","volume":"87993"},{"date":"20091125","ticker":"DHI","open":"10.7","high":"10.9","low":"10.6","close":"10.66","volume":"60433"},{"date":"20091127","ticker":"DHI","open":"10.26","high":"10.62","low":"10.05","close":"10.54","volume":"32793"},{"date":"20091130","ticker":"DHI","open":"10.45","high":"10.61","low":"10.17","close":"10.28","volume":"76018"},{"date":"20091201","ticker":"DHI","open":"10.4","high":"10.53","low":"10.22","close":"10.42","volume":"61511"},{"date":"20091202","ticker":"DHI","open":"10.33","high":"10.51","low":"9.78","close":"10.04","volume":"155602"},{"date":"20091203","ticker":"DHI","open":"10.14","high":"10.16","low":"9.93","close":"10","volume":"88916"},{"date":"20091204","ticker":"DHI","open":"10.16","high":"10.36","low":"9.89","close":"10.1","volume":"87459"},{"date":"20091207","ticker":"DHI","open":"9.99","high":"10.2","low":"9.865","close":"9.9","volume":"90100"},{"date":"20091208","ticker":"DHI","open":"9.81","high":"10.06","low":"9.71","close":"9.85","volume":"62465"},{"date":"20091209","ticker":"DHI","open":"9.97","high":"9.97","low":"9.69","close":"9.84","volume":"48746"},{"date":"20091210","ticker":"DHI","open":"9.93","high":"10.07","low":"9.84","close":"9.89","volume":"60657"},{"date":"20091211","ticker":"DHI","open":"9.92","high":"9.9785","low":"9.71","close":"9.86","volume":"41815"},{"date":"20091214","ticker":"DHI","open":"9.98","high":"10.09","low":"9.73","close":"10.07","volume":"38322"},{"date":"20091215","ticker":"DHI","open":"10.07","high":"10.17","low":"9.78","close":"9.81","volume":"50547"},{"date":"20091216","ticker":"DHI","open":"9.94","high":"10.37","low":"9.87","close":"10.29","volume":"74415"},{"date":"20091217","ticker":"DHI","open":"10.17","high":"10.34","low":"10.08","close":"10.25","volume":"60182"},{"date":"20091218","ticker":"DHI","open":"10.31","high":"10.53","low":"10.21","close":"10.53","volume":"114526"},{"date":"20091221","ticker":"DHI","open":"10.79","high":"10.8","low":"10.5","close":"10.74","volume":"63023"},{"date":"20091222","ticker":"DHI","open":"10.76","high":"11.17","low":"10.71","close":"11.15","volume":"93599"},{"date":"20091223","ticker":"DHI","open":"11.28","high":"11.33","low":"10.99","close":"11.12","volume":"79780"},{"date":"20091224","ticker":"DHI","open":"11.09","high":"11.14","low":"11.05","close":"11.12","volume":"15890"},{"date":"20091228","ticker":"DHI","open":"11.14","high":"11.25","low":"10.84","close":"10.96","volume":"53858"},{"date":"20091229","ticker":"DHI","open":"10.97","high":"11.12","low":"10.75","close":"10.93","volume":"49061"},{"date":"20091230","ticker":"DHI","open":"10.79","high":"11.1","low":"10.76","close":"10.99","volume":"40139"},{"date":"20091231","ticker":"DHI","open":"10.94","high":"11.03","low":"10.83","close":"10.87","volume":"29864"},{"date":"20100104","ticker":"DHI","open":"10.96","high":"11.18","low":"10.87","close":"11.16","volume":"57990"},{"date":"20100105","ticker":"DHI","open":"11.1","high":"11.59","low":"10.945","close":"11.56","volume":"102544"},{"date":"20100106","ticker":"DHI","open":"11.45","high":"11.76","low":"11.39","close":"11.66","volume":"84102"},{"date":"20100107","ticker":"DHI","open":"11.94","high":"12.6333","low":"11.92","close":"12.27","volume":"138087"},{"date":"20100108","ticker":"DHI","open":"12.12","high":"12.31","low":"12.04","close":"12.17","volume":"57206"},{"date":"20100111","ticker":"DHI","open":"12.29","high":"12.32","low":"12.02","close":"12.24","volume":"37460"},{"date":"20100112","ticker":"DHI","open":"12.09","high":"12.225","low":"11.85","close":"12.21","volume":"59820"},{"date":"20100113","ticker":"DHI","open":"12.24","high":"12.57","low":"12.04","close":"12.42","volume":"62783"},{"date":"20100114","ticker":"DHI","open":"12.33","high":"12.56","low":"12.23","close":"12.25","volume":"43447"},{"date":"20100115","ticker":"DHI","open":"12.19","high":"12.38","low":"11.94","close":"12.14","volume":"46860"},{"date":"20100119","ticker":"DHI","open":"12.1","high":"12.495","low":"12.09","close":"12.33","volume":"44561"},{"date":"20100120","ticker":"DHI","open":"12.16","high":"12.32","low":"12.08","close":"12.13","volume":"51945"},{"date":"20100121","ticker":"DHI","open":"12.11","high":"12.17","low":"11.52","close":"11.55","volume":"72756"},{"date":"20100122","ticker":"DHI","open":"11.52","high":"11.86","low":"11.11","close":"11.2","volume":"117475"},{"date":"20100125","ticker":"DHI","open":"11.3","high":"11.58","low":"11.17","close":"11.37","volume":"60310"},{"date":"20100126","ticker":"DHI","open":"11.25","high":"11.59","low":"11.2","close":"11.29","volume":"72662"},{"date":"20100127","ticker":"DHI","open":"11.21","high":"11.72","low":"11.17","close":"11.67","volume":"90993"},{"date":"20100128","ticker":"DHI","open":"11.78","high":"12.04","low":"11.53","close":"11.79","volume":"94370"},{"date":"20100129","ticker":"DHI","open":"11.96","high":"12.12","low":"11.77","close":"11.79","volume":"67884"},{"date":"20100201","ticker":"DHI","open":"11.83","high":"12.04","low":"11.63","close":"11.91","volume":"68157"},{"date":"20100202","ticker":"DHI","open":"12.79","high":"13.355","low":"12.23","close":"13.21","volume":"288143"},{"date":"20100203","ticker":"DHI","open":"13.27","high":"13.305","low":"12.81","close":"13.25","volume":"117121"},{"date":"20100204","ticker":"DHI","open":"13.03","high":"13.34","low":"12.94","close":"13.21","volume":"137177"},{"date":"20100205","ticker":"DHI","open":"13.08","high":"13.14","low":"12.16","close":"12.67","volume":"143734"},{"date":"20100208","ticker":"DHI","open":"12.72","high":"13.26","low":"12.47","close":"12.92","volume":"86915"},{"date":"20100209","ticker":"DHI","open":"13.08","high":"13.16","low":"12.605","close":"12.98","volume":"84932"},{"date":"20100210","ticker":"DHI","open":"12.97","high":"13.07","low":"12.59","close":"12.85","volume":"73130"},{"date":"20100211","ticker":"DHI","open":"12.85","high":"13.22","low":"12.695","close":"13.12","volume":"65258"},{"date":"20100212","ticker":"DHI","open":"13.25","high":"13.42","low":"12.96","close":"13.07","volume":"83256"},{"date":"20100216","ticker":"DHI","open":"13.3","high":"13.33","low":"13.05","close":"13.22","volume":"45824"},{"date":"20100217","ticker":"DHI","open":"13.43","high":"13.53","low":"12.94","close":"13.12","volume":"69247"},{"date":"20100218","ticker":"DHI","open":"12.98","high":"13.03","low":"12.69","close":"12.78","volume":"72085"},{"date":"20100219","ticker":"DHI","open":"12.74","high":"13","low":"12.74","close":"12.95","volume":"77251"},{"date":"20100222","ticker":"DHI","open":"13","high":"13.09","low":"12.77","close":"12.92","volume":"62027"},{"date":"20100223","ticker":"DHI","open":"12.88","high":"12.975","low":"12.43","close":"12.57","volume":"95564"},{"date":"20100224","ticker":"DHI","open":"12.63","high":"12.65","low":"12.04","close":"12.34","volume":"94375"},{"date":"20100225","ticker":"DHI","open":"12.08","high":"12.35","low":"11.96","close":"12.35","volume":"60017"},{"date":"20100226","ticker":"DHI","open":"12.37","high":"12.45","low":"12.02","close":"12.36","volume":"52503"},{"date":"20100301","ticker":"DHI","open":"12.37","high":"12.585","low":"12.37","close":"12.56","volume":"38737"},{"date":"20100302","ticker":"DHI","open":"12.66","high":"12.72","low":"12.4","close":"12.47","volume":"38059"},{"date":"20100303","ticker":"DHI","open":"12.56","high":"12.8","low":"12.465","close":"12.57","volume":"54716"},{"date":"20100304","ticker":"DHI","open":"12.59","high":"12.72","low":"12.31","close":"12.49","volume":"44049"},{"date":"20100305","ticker":"DHI","open":"12.58","high":"12.95","low":"12.55","close":"12.87","volume":"64969"},{"date":"20100308","ticker":"DHI","open":"12.87","high":"12.99","low":"12.79","close":"12.96","volume":"28706"},{"date":"20100309","ticker":"DHI","open":"12.91","high":"13.17","low":"12.83","close":"13.09","volume":"50213"},{"date":"20100310","ticker":"DHI","open":"13.1","high":"13.23","low":"12.9","close":"13.01","volume":"50131"},{"date":"20100311","ticker":"DHI","open":"12.95","high":"12.98","low":"12.73","close":"12.96","volume":"43454"},{"date":"20100312","ticker":"DHI","open":"12.99","high":"13.01","low":"12.78","close":"13","volume":"45720"},{"date":"20100315","ticker":"DHI","open":"12.98","high":"13.029","low":"12.64","close":"12.84","volume":"35303"},{"date":"20100316","ticker":"DHI","open":"12.8","high":"13.15","low":"12.6","close":"13.03","volume":"50426"},{"date":"20100317","ticker":"DHI","open":"13.05","high":"13.17","low":"12.79","close":"12.89","volume":"48752"},{"date":"20100318","ticker":"DHI","open":"12.93","high":"12.99","low":"12.66","close":"12.76","volume":"29390"},{"date":"20100319","ticker":"DHI","open":"12.81","high":"12.93","low":"12.5","close":"12.51","volume":"55931"},{"date":"20100322","ticker":"DHI","open":"12.4","high":"12.79","low":"12.37","close":"12.75","volume":"33722"},{"date":"20100323","ticker":"DHI","open":"12.83","high":"12.88","low":"12.65","close":"12.76","volume":"51373"},{"date":"20100324","ticker":"DHI","open":"12.95","high":"13.07","low":"12.76","close":"12.85","volume":"52724"},{"date":"20100325","ticker":"DHI","open":"12.91","high":"13.4","low":"12.91","close":"12.97","volume":"61700"},{"date":"20100326","ticker":"DHI","open":"13.03","high":"13.38","low":"12.97","close":"13.13","volume":"44007"},{"date":"20100329","ticker":"DHI","open":"13.21","high":"13.23","low":"12.74","close":"13.03","volume":"50741"},{"date":"20100330","ticker":"DHI","open":"12.99","high":"13.11","low":"12.72","close":"12.8","volume":"40758"},{"date":"20100331","ticker":"DHI","open":"12.73","high":"12.87","low":"12.53","close":"12.6","volume":"54078"},{"date":"20100401","ticker":"DHI","open":"12.72","high":"12.81","low":"12.4","close":"12.51","volume":"40378"},{"date":"20100405","ticker":"DHI","open":"12.62","high":"12.79","low":"12.46","close":"12.59","volume":"43647"},{"date":"20100406","ticker":"DHI","open":"12.52","high":"12.59","low":"12.32","close":"12.52","volume":"55899"},{"date":"20100407","ticker":"DHI","open":"12.54","high":"12.55","low":"11.86","close":"11.93","volume":"115183"},{"date":"20100408","ticker":"DHI","open":"11.9","high":"12.03","low":"11.75","close":"12.01","volume":"79148"},{"date":"20100409","ticker":"DHI","open":"12.04","high":"12.185","low":"11.98","close":"12.14","volume":"38701"},{"date":"20100412","ticker":"DHI","open":"12.19","high":"12.24","low":"11.89","close":"12.03","volume":"67469"},{"date":"20100413","ticker":"DHI","open":"12.04","high":"12.27","low":"12.01","close":"12.18","volume":"69399"},{"date":"20100414","ticker":"DHI","open":"12.25","high":"12.81","low":"12.24","close":"12.65","volume":"101835"},{"date":"20100415","ticker":"DHI","open":"12.63","high":"12.74","low":"12.51","close":"12.6","volume":"56106"},{"date":"20100416","ticker":"DHI","open":"12.5","high":"12.58","low":"12.025","close":"12.37","volume":"93481"},{"date":"20100419","ticker":"DHI","open":"12.32","high":"12.4","low":"12.04","close":"12.34","volume":"48289"},{"date":"20100420","ticker":"DHI","open":"12.41","high":"12.79","low":"12.255","close":"12.76","volume":"59225"},{"date":"20100421","ticker":"DHI","open":"12.77","high":"13.1","low":"12.65","close":"12.98","volume":"63332"},{"date":"20100422","ticker":"DHI","open":"12.92","high":"13.855","low":"12.77","close":"13.69","volume":"112278"},{"date":"20100423","ticker":"DHI","open":"13.79","high":"14.54","low":"13.72","close":"14.17","volume":"123148"},{"date":"20100426","ticker":"DHI","open":"14.23","high":"14.48","low":"13.81","close":"13.88","volume":"63999"},{"date":"20100427","ticker":"DHI","open":"13.75","high":"14.03","low":"13.37","close":"13.41","volume":"91512"},{"date":"20100428","ticker":"DHI","open":"13.48","high":"50.8","low":"13.47","close":"13.62","volume":"74409"},{"date":"20100429","ticker":"DHI","open":"13.75","high":"14.42","low":"13.63","close":"14.24","volume":"111553"},{"date":"20100430","ticker":"DHI","open":"15.07","high":"15.44","low":"14.63","close":"14.69","volume":"154285"},{"date":"20100503","ticker":"DHI","open":"14.71","high":"15.2","low":"14.64","close":"14.97","volume":"70491"},{"date":"20100504","ticker":"DHI","open":"14.75","high":"14.82","low":"14.22","close":"14.63","volume":"86924"},{"date":"20100505","ticker":"DHI","open":"14.4","high":"14.62","low":"14.03","close":"14.14","volume":"77508"},{"date":"20100506","ticker":"DHI","open":"14","high":"14.38","low":"12.64","close":"13.65","volume":"108580"},{"date":"20100507","ticker":"DHI","open":"13.68","high":"13.87","low":"12.92","close":"13.06","volume":"99551"},{"date":"20100510","ticker":"DHI","open":"13.67","high":"14.01","low":"13.37","close":"13.94","volume":"81169"},{"date":"20100511","ticker":"DHI","open":"13.68","high":"14.38","low":"13.54","close":"13.84","volume":"89447"},{"date":"20100512","ticker":"DHI","open":"13.93","high":"14.18","low":"13.82","close":"14.04","volume":"50532"},{"date":"20100513","ticker":"DHI","open":"14.02","high":"14.02","low":"13.33","close":"13.46","volume":"72709"},{"date":"20100514","ticker":"DHI","open":"13.29","high":"13.34","low":"12.81","close":"13.11","volume":"69260"},{"date":"20100517","ticker":"DHI","open":"13.08","high":"13.32","low":"12.62","close":"13.3","volume":"75588"},{"date":"20100518","ticker":"DHI","open":"13.42","high":"13.75","low":"12.96","close":"13.02","volume":"76647"},{"date":"20100519","ticker":"DHI","open":"12.81","high":"13.3","low":"12.38","close":"12.67","volume":"141218"},{"date":"20100520","ticker":"DHI","open":"12.29","high":"12.56","low":"12.13","close":"12.14","volume":"110594"},{"date":"20100521","ticker":"DHI","open":"12.02","high":"12.4684","low":"11.86","close":"12.26","volume":"109993"},{"date":"20100524","ticker":"DHI","open":"12.19","high":"12.57","low":"12.05","close":"12.06","volume":"64159"},{"date":"20100525","ticker":"DHI","open":"11.67","high":"12.14","low":"11.57","close":"12.1","volume":"104797"},{"date":"20100526","ticker":"DHI","open":"12.43","high":"12.67","low":"11.97","close":"12.01","volume":"95058"},{"date":"20100527","ticker":"DHI","open":"12.25","high":"12.35","low":"11.92","close":"12.34","volume":"58922"},{"date":"20100528","ticker":"DHI","open":"12.32","high":"12.48","low":"12.12","close":"12.19","volume":"48966"},{"date":"20100601","ticker":"DHI","open":"12.1","high":"12.29","low":"11.76","close":"11.77","volume":"75995"},{"date":"20100602","ticker":"DHI","open":"11.78","high":"12.16","low":"11.75","close":"12.13","volume":"64535"},{"date":"20100603","ticker":"DHI","open":"12.13","high":"12.21","low":"11.69","close":"11.78","volume":"78210"},{"date":"20100604","ticker":"DHI","open":"11.6","high":"11.68","low":"11.25","close":"11.34","volume":"72681"},{"date":"20100607","ticker":"DHI","open":"11.39","high":"11.46","low":"10.82","close":"10.89","volume":"64236"},{"date":"20100608","ticker":"DHI","open":"10.92","high":"11.05","low":"10.44","close":"10.84","volume":"131892"},{"date":"20100609","ticker":"DHI","open":"11.08","high":"11.1","low":"10.46","close":"10.54","volume":"110135"},{"date":"20100610","ticker":"DHI","open":"10.79","high":"11.41","low":"10.6392","close":"11.3","volume":"138522"},{"date":"20100611","ticker":"DHI","open":"11.15","high":"11.28","low":"10.97","close":"11.26","volume":"63014"},{"date":"20100614","ticker":"DHI","open":"11.35","high":"11.41","low":"10.99","close":"11.07","volume":"67270"},{"date":"20100615","ticker":"DHI","open":"11.16","high":"11.39","low":"11.07","close":"11.39","volume":"72290"},{"date":"20100616","ticker":"DHI","open":"11.22","high":"11.49","low":"11.07","close":"11.24","volume":"77644"},{"date":"20100617","ticker":"DHI","open":"11.19","high":"11.22","low":"10.63","close":"10.94","volume":"82669"},{"date":"20100618","ticker":"DHI","open":"10.92","high":"10.96","low":"10.66","close":"10.75","volume":"59399"},{"date":"20100621","ticker":"DHI","open":"10.9","high":"10.99","low":"10.48","close":"10.54","volume":"75845"},{"date":"20100622","ticker":"DHI","open":"10.52","high":"10.67","low":"10.16","close":"10.22","volume":"81665"},{"date":"20100623","ticker":"DHI","open":"10.22","high":"10.6","low":"10.03","close":"10.47","volume":"85873"},{"date":"20100624","ticker":"DHI","open":"10.48","high":"10.76","low":"10.29","close":"10.58","volume":"101041"},{"date":"20100625","ticker":"DHI","open":"10.57","high":"10.57","low":"10.26","close":"10.47","volume":"71931"},{"date":"20100628","ticker":"DHI","open":"10.5","high":"10.59","low":"10.29","close":"10.36","volume":"86558"},{"date":"20100629","ticker":"DHI","open":"10.3","high":"10.39","low":"9.85","close":"9.96","volume":"95902"},{"date":"20100630","ticker":"DHI","open":"9.96","high":"10.15","low":"9.82","close":"9.83","volume":"92595"},{"date":"20100701","ticker":"DHI","open":"9.78","high":"10","low":"9.58","close":"9.85","volume":"118264"},{"date":"20100702","ticker":"DHI","open":"9.89","high":"9.89","low":"9.41","close":"9.71","volume":"95166"},{"date":"20100706","ticker":"DHI","open":"9.88","high":"10.05","low":"9.7","close":"9.79","volume":"110932"},{"date":"20100707","ticker":"DHI","open":"9.8","high":"10.23","low":"9.775","close":"10.2","volume":"83742"},{"date":"20100708","ticker":"DHI","open":"10.29","high":"10.42","low":"9.74","close":"9.8","volume":"166530"},{"date":"20100709","ticker":"DHI","open":"9.81","high":"10.35","low":"9.78","close":"10.25","volume":"61343"},{"date":"20100712","ticker":"DHI","open":"10.23","high":"10.27","low":"9.98","close":"10.1","volume":"38194"},{"date":"20100713","ticker":"DHI","open":"10.17","high":"10.5","low":"10.1075","close":"10.43","volume":"65541"},{"date":"20100714","ticker":"DHI","open":"10.33","high":"10.36","low":"10.06","close":"10.34","volume":"66239"},{"date":"20100715","ticker":"DHI","open":"10.35","high":"10.69","low":"10.2","close":"10.62","volume":"103381"},{"date":"20100716","ticker":"DHI","open":"10.55","high":"10.57","low":"10.03","close":"10.1","volume":"74508"},{"date":"20100719","ticker":"DHI","open":"10.17","high":"10.21","low":"9.85","close":"9.97","volume":"65190"},{"date":"20100720","ticker":"DHI","open":"9.8","high":"10.48","low":"9.72","close":"10.39","volume":"61981"},{"date":"20100721","ticker":"DHI","open":"10.51","high":"10.54","low":"10.15","close":"10.2","volume":"60966"},{"date":"20100722","ticker":"DHI","open":"10.33","high":"10.74","low":"10.31","close":"10.55","volume":"53182"},{"date":"20100723","ticker":"DHI","open":"10.5","high":"10.9","low":"10.41","close":"10.85","volume":"54987"},{"date":"20100726","ticker":"DHI","open":"10.82","high":"11.2701","low":"10.76","close":"11.17","volume":"79047"},{"date":"20100727","ticker":"DHI","open":"11.24","high":"11.38","low":"11.01","close":"11.08","volume":"84495"},{"date":"20100728","ticker":"DHI","open":"11.07","high":"11.14","low":"10.55","close":"10.64","volume":"51520"},{"date":"20100729","ticker":"DHI","open":"10.76","high":"11.01","low":"10.5775","close":"10.88","volume":"83513"},{"date":"20100730","ticker":"DHI","open":"10.74","high":"11.09","low":"10.61","close":"11.02","volume":"73305"},{"date":"20100802","ticker":"DHI","open":"11.22","high":"11.38","low":"10.94","close":"11.25","volume":"70449"},{"date":"20100803","ticker":"DHI","open":"11.09","high":"11.3","low":"10.48","close":"10.6","volume":"122024"},{"date":"20100804","ticker":"DHI","open":"10.65","high":"10.82","low":"10.46","close":"10.48","volume":"46427"},{"date":"20100805","ticker":"DHI","open":"10.31","high":"10.53","low":"10.28","close":"10.42","volume":"45848"},{"date":"20100806","ticker":"DHI","open":"10.33","high":"10.66","low":"10.24","close":"10.6","volume":"55464"},{"date":"20100809","ticker":"DHI","open":"10.9","high":"11.14","low":"10.76","close":"11.06","volume":"61510"},{"date":"20100810","ticker":"DHI","open":"10.9","high":"10.98","low":"10.72","close":"10.83","volume":"48069"},{"date":"20100811","ticker":"DHI","open":"10.61","high":"10.67","low":"10.46","close":"10.54","volume":"57940"},{"date":"20100812","ticker":"DHI","open":"10.27","high":"10.47","low":"10.185","close":"10.21","volume":"44969"},{"date":"20100813","ticker":"DHI","open":"10.18","high":"10.38","low":"10.13","close":"10.24","volume":"45157"},{"date":"20100816","ticker":"DHI","open":"10.15","high":"10.34","low":"10.085","close":"10.18","volume":"31624"},{"date":"20100817","ticker":"DHI","open":"10.31","high":"10.58","low":"10.19","close":"10.47","volume":"41535"},{"date":"20100819","ticker":"DHI","open":"10.56","high":"10.58","low":"10.34","close":"10.43","volume":"43980"},{"date":"20100820","ticker":"DHI","open":"10.32","high":"10.39","low":"10.19","close":"10.27","volume":"45866"}]