[{"date":"20090821","ticker":"HUM","open":"36.21","high":"36.34","low":"35.58","close":"36.05","volume":"13999"},{"date":"20090824","ticker":"HUM","open":"36.49","high":"37.25","low":"36.16","close":"36.93","volume":"21121"},{"date":"20090825","ticker":"HUM","open":"37.11","high":"37.59","low":"36.74","close":"37.16","volume":"20256"},{"date":"20090826","ticker":"HUM","open":"37.08","high":"37.14","low":"36.09","close":"36.15","volume":"22064"},{"date":"20090827","ticker":"HUM","open":"35.93","high":"37.17","low":"35.87","close":"37.02","volume":"19832"},{"date":"20090828","ticker":"HUM","open":"37.38","high":"37.38","low":"35.82","close":"36.23","volume":"15160"},{"date":"20090831","ticker":"HUM","open":"35.88","high":"37","low":"35.43","close":"35.7","volume":"15172"},{"date":"20090901","ticker":"HUM","open":"35.65","high":"36.38","low":"35.08","close":"35.32","volume":"19412"},{"date":"20090902","ticker":"HUM","open":"35.6","high":"37.39","low":"35.35","close":"37.1","volume":"31980"},{"date":"20090903","ticker":"HUM","open":"37.02","high":"37.94","low":"36.66","close":"37.14","volume":"23376"},{"date":"20090904","ticker":"HUM","open":"37.32","high":"38.18","low":"37.14","close":"37.79","volume":"14239"},{"date":"20090909","ticker":"HUM","open":"36.78","high":"38.19","low":"36.71","close":"38.07","volume":"34231"},{"date":"20090910","ticker":"HUM","open":"37.87","high":"39.6","low":"37.8","close":"39.54","volume":"34718"},{"date":"20090911","ticker":"HUM","open":"39.8","high":"39.9","low":"39.24","close":"39.49","volume":"21351"},{"date":"20090914","ticker":"HUM","open":"39.55","high":"39.85","low":"38.54","close":"39.45","volume":"24342"},{"date":"20090915","ticker":"HUM","open":"39.15","high":"39.33","low":"38.46","close":"38.78","volume":"26743"},{"date":"20090916","ticker":"HUM","open":"38.98","high":"40.74","low":"38.68","close":"40.67","volume":"30041"},{"date":"20090917","ticker":"HUM","open":"40.78","high":"41","low":"39.75","close":"40.21","volume":"18086"},{"date":"20090918","ticker":"HUM","open":"40.25","high":"40.67","low":"39.6101","close":"39.89","volume":"17726"},{"date":"20090921","ticker":"HUM","open":"38.91","high":"40.24","low":"38.89","close":"39.75","volume":"20860"},{"date":"20090922","ticker":"HUM","open":"39.69","high":"39.8","low":"38.78","close":"39.51","volume":"18656"},{"date":"20090923","ticker":"HUM","open":"39.5","high":"39.75","low":"38.82","close":"39.02","volume":"21876"},{"date":"20090924","ticker":"HUM","open":"39.05","high":"39.52","low":"37.86","close":"38.19","volume":"21705"},{"date":"20090925","ticker":"HUM","open":"37.82","high":"38.6","low":"37.16","close":"37.6","volume":"27374"},{"date":"20090928","ticker":"HUM","open":"37.62","high":"38.65","low":"37.56","close":"38.03","volume":"19175"},{"date":"20090929","ticker":"HUM","open":"38.18","high":"39.28","low":"37.25","close":"38.02","volume":"45987"},{"date":"20090930","ticker":"HUM","open":"37.25","high":"37.43","low":"36.5","close":"37.3","volume":"34803"},{"date":"20091001","ticker":"HUM","open":"37.39","high":"38.11","low":"36.91","close":"37.28","volume":"35964"},{"date":"20091002","ticker":"HUM","open":"37.2","high":"37.2","low":"35.98","close":"36.68","volume":"29074"},{"date":"20091005","ticker":"HUM","open":"36.99","high":"37.38","low":"36.23","close":"37.15","volume":"22891"},{"date":"20091006","ticker":"HUM","open":"37.29","high":"37.7399","low":"36.65","close":"37.26","volume":"23263"},{"date":"20091007","ticker":"HUM","open":"37.24","high":"38.39","low":"37.08","close":"37.9","volume":"20472"},{"date":"20091008","ticker":"HUM","open":"37.09","high":"37.365","low":"35.66","close":"35.91","volume":"56969"},{"date":"20091009","ticker":"HUM","open":"35.98","high":"37.61","low":"35.98","close":"37.29","volume":"25953"},{"date":"20091012","ticker":"HUM","open":"37.56","high":"38.83","low":"37.39","close":"38.1","volume":"27384"},{"date":"20091013","ticker":"HUM","open":"38.07","high":"38.83","low":"37.22","close":"37.67","volume":"39722"},{"date":"20091014","ticker":"HUM","open":"37.95","high":"38.61","low":"37.583","close":"38.02","volume":"29346"},{"date":"20091015","ticker":"HUM","open":"37.87","high":"37.99","low":"37.03","close":"37.26","volume":"28165"},{"date":"20091016","ticker":"HUM","open":"37.05","high":"37.7","low":"36.87","close":"36.95","volume":"26583"},{"date":"20091019","ticker":"HUM","open":"37.26","high":"37.56","low":"36.94","close":"37.13","volume":"20859"},{"date":"20091020","ticker":"HUM","open":"37.32","high":"38.85","low":"37.32","close":"38.04","volume":"27972"},{"date":"20091021","ticker":"HUM","open":"38.095","high":"38.48","low":"36.99","close":"37.06","volume":"18961"},{"date":"20091022","ticker":"HUM","open":"37.42","high":"38.07","low":"37.095","close":"37.79","volume":"22600"},{"date":"20091023","ticker":"HUM","open":"38.17","high":"38.53","low":"37.34","close":"37.54","volume":"19624"},{"date":"20091026","ticker":"HUM","open":"37.62","high":"37.81","low":"36.05","close":"36.21","volume":"26262"},{"date":"20091027","ticker":"HUM","open":"36.17","high":"37.97","low":"35.8","close":"37.47","volume":"28606"},{"date":"20091028","ticker":"HUM","open":"37.25","high":"37.62","low":"36.5","close":"36.68","volume":"22651"},{"date":"20091105","ticker":"HUM","open":"39.19","high":"40.27","low":"38.98","close":"39.91","volume":"24812"},{"date":"20091106","ticker":"HUM","open":"39.82","high":"40.55","low":"39.44","close":"40.45","volume":"14855"},{"date":"20091109","ticker":"HUM","open":"40.35","high":"41.6","low":"39.958","close":"41.51","volume":"22895"},{"date":"20091110","ticker":"HUM","open":"41.11","high":"41.97","low":"41.08","close":"41.81","volume":"18502"},{"date":"20091111","ticker":"HUM","open":"41.34","high":"41.81","low":"41.16","close":"41.71","volume":"16551"},{"date":"20091112","ticker":"HUM","open":"41.65","high":"41.67","low":"40.63","close":"40.8","volume":"17016"},{"date":"20091113","ticker":"HUM","open":"40.99","high":"41.71","low":"40.86","close":"41.1","volume":"18401"},{"date":"20091116","ticker":"HUM","open":"41.43","high":"42.21","low":"41.09","close":"41.35","volume":"27498"},{"date":"20091117","ticker":"HUM","open":"41.28","high":"41.56","low":"40.88","close":"41.11","volume":"15665"},{"date":"20091118","ticker":"HUM","open":"41.19","high":"41.48","low":"40.45","close":"40.95","volume":"18451"},{"date":"20091119","ticker":"HUM","open":"40.88","high":"40.91","low":"39.76","close":"40.83","volume":"15287"},{"date":"20091120","ticker":"HUM","open":"40.86","high":"40.86","low":"40.15","close":"40.44","volume":"15636"},{"date":"20091123","ticker":"HUM","open":"40.95","high":"42.26","low":"40.94","close":"41.48","volume":"21457"},{"date":"20091124","ticker":"HUM","open":"41.37","high":"42.09","low":"40.98","close":"41.86","volume":"15193"},{"date":"20091125","ticker":"HUM","open":"41.86","high":"42.21","low":"41.58","close":"42.1","volume":"10521"},{"date":"20091127","ticker":"HUM","open":"40.94","high":"42","low":"40.5","close":"41.73","volume":"5863"},{"date":"20091130","ticker":"HUM","open":"41.99","high":"42.09","low":"40.8101","close":"41.51","volume":"15722"},{"date":"20091201","ticker":"HUM","open":"41.72","high":"42.54","low":"41.72","close":"42.46","volume":"14518"},{"date":"20091202","ticker":"HUM","open":"42.41","high":"42.79","low":"42.15","close":"42.54","volume":"16296"},{"date":"20091203","ticker":"HUM","open":"42.77","high":"42.81","low":"40.47","close":"40.53","volume":"27259"},{"date":"20091204","ticker":"HUM","open":"41.19","high":"41.55","low":"40.15","close":"40.31","volume":"30949"},{"date":"20091207","ticker":"HUM","open":"40.93","high":"41.99","low":"40.1","close":"40.61","volume":"27228"},{"date":"20091208","ticker":"HUM","open":"41.06","high":"41.57","low":"40.34","close":"40.51","volume":"26470"},{"date":"20091209","ticker":"HUM","open":"40.95","high":"41.73","low":"40.45","close":"40.88","volume":"29080"},{"date":"20091210","ticker":"HUM","open":"41.04","high":"42.26","low":"40.95","close":"42.04","volume":"38522"},{"date":"20091211","ticker":"HUM","open":"42.09","high":"42.6","low":"41.68","close":"41.84","volume":"24249"},{"date":"20091214","ticker":"HUM","open":"42.1","high":"42.8","low":"42.1","close":"42.42","volume":"26853"},{"date":"20091215","ticker":"HUM","open":"42.09","high":"43.55","low":"41.96","close":"43.15","volume":"32778"},{"date":"20091216","ticker":"HUM","open":"43.46","high":"44.57","low":"43.29","close":"43.84","volume":"37713"},{"date":"20091217","ticker":"HUM","open":"44.09","high":"44.09","low":"42.65","close":"43.48","volume":"20391"},{"date":"20091218","ticker":"HUM","open":"43.89","high":"43.89","low":"43.02","close":"43.53","volume":"27696"},{"date":"20091221","ticker":"HUM","open":"44.21","high":"45.89","low":"44.16","close":"45.04","volume":"32027"},{"date":"20091222","ticker":"HUM","open":"45.69","high":"45.69","low":"45.12","close":"45.27","volume":"24736"},{"date":"20091223","ticker":"HUM","open":"45.28","high":"46.2","low":"45.21","close":"45.75","volume":"21397"},{"date":"20091224","ticker":"HUM","open":"45.86","high":"45.87","low":"45.16","close":"45.44","volume":"12196"},{"date":"20091228","ticker":"HUM","open":"45.44","high":"45.67","low":"45.13","close":"45.42","volume":"13921"},{"date":"20091229","ticker":"HUM","open":"45.38","high":"45.59","low":"44.7","close":"44.9","volume":"14097"},{"date":"20091230","ticker":"HUM","open":"44.75","high":"44.77","low":"44.09","close":"44.38","volume":"11271"},{"date":"20091231","ticker":"HUM","open":"44.5","high":"44.575","low":"43.78","close":"43.89","volume":"8315"},{"date":"20100104","ticker":"HUM","open":"44.43","high":"45.77","low":"44.43","close":"45.68","volume":"20084"},{"date":"20100105","ticker":"HUM","open":"45.79","high":"46.16","low":"45.27","close":"45.66","volume":"18606"},{"date":"20100106","ticker":"HUM","open":"45.66","high":"46.34","low":"45.35","close":"45.98","volume":"16867"},{"date":"20100107","ticker":"HUM","open":"46.25","high":"48.69","low":"46.25","close":"48.12","volume":"37065"},{"date":"20100108","ticker":"HUM","open":"47.81","high":"48.02","low":"47.2","close":"47.51","volume":"24123"},{"date":"20100111","ticker":"HUM","open":"47.44","high":"47.729","low":"46.71","close":"46.95","volume":"20008"},{"date":"20100112","ticker":"HUM","open":"46.48","high":"46.78","low":"45.62","close":"46.18","volume":"23920"},{"date":"20100113","ticker":"HUM","open":"46.24","high":"47.14","low":"45.32","close":"47.03","volume":"24557"},{"date":"20100114","ticker":"HUM","open":"46.76","high":"48.6","low":"46.75","close":"48.02","volume":"34333"},{"date":"20100115","ticker":"HUM","open":"48.14","high":"48.99","low":"47.59","close":"48.51","volume":"26465"},{"date":"20100119","ticker":"HUM","open":"49.3","high":"52.26","low":"49.3","close":"51.94","volume":"95725"},{"date":"20100120","ticker":"HUM","open":"52.65","high":"52.66","low":"50.3","close":"51.27","volume":"109260"},{"date":"20100121","ticker":"HUM","open":"51.13","high":"52.18","low":"51.01","close":"51.77","volume":"90716"},{"date":"20100122","ticker":"HUM","open":"51.7","high":"52.58","low":"50.82","close":"51","volume":"38840"},{"date":"20100125","ticker":"HUM","open":"50.89","high":"51.41","low":"49.4","close":"49.56","volume":"45852"},{"date":"20100126","ticker":"HUM","open":"49.6","high":"49.69","low":"48.1","close":"48.27","volume":"37605"},{"date":"20100127","ticker":"HUM","open":"48.25","high":"50.11","low":"47.811","close":"49.02","volume":"32321"},{"date":"20100128","ticker":"HUM","open":"49.26","high":"50.21","low":"48.43","close":"48.79","volume":"33183"},{"date":"20100129","ticker":"HUM","open":"49.11","high":"49.71","low":"48.54","close":"48.62","volume":"26709"},{"date":"20100201","ticker":"HUM","open":"48","high":"50.37","low":"46.18","close":"48.71","volume":"87987"},{"date":"20100202","ticker":"HUM","open":"48.93","high":"50.34","low":"48.53","close":"50.3","volume":"25962"},{"date":"20100203","ticker":"HUM","open":"50.22","high":"50.3275","low":"48.53","close":"48.98","volume":"22569"},{"date":"20100204","ticker":"HUM","open":"48.9","high":"48.9","low":"47.16","close":"47.17","volume":"21657"},{"date":"20100205","ticker":"HUM","open":"46.66","high":"47.2","low":"45.65","close":"47.02","volume":"31504"},{"date":"20100208","ticker":"HUM","open":"46.99","high":"47.71","low":"46.5","close":"46.75","volume":"13838"},{"date":"20100209","ticker":"HUM","open":"47.35","high":"48.34","low":"46.26","close":"47.92","volume":"31311"},{"date":"20100210","ticker":"HUM","open":"48.01","high":"48.01","low":"45.8901","close":"47.1","volume":"27331"},{"date":"20100211","ticker":"HUM","open":"47.29","high":"47.33","low":"46.3","close":"46.82","volume":"20817"},{"date":"20100212","ticker":"HUM","open":"46.3","high":"46.3","low":"45.43","close":"45.95","volume":"22169"},{"date":"20100216","ticker":"HUM","open":"46.34","high":"46.45","low":"45.24","close":"46.01","volume":"14995"},{"date":"20100217","ticker":"HUM","open":"46.22","high":"47.3","low":"46.18","close":"46.64","volume":"17014"},{"date":"20100218","ticker":"HUM","open":"46.39","high":"46.91","low":"45.89","close":"46.2","volume":"24702"},{"date":"20100219","ticker":"HUM","open":"45.82","high":"46.11","low":"45.07","close":"45.35","volume":"39601"},{"date":"20100222","ticker":"HUM","open":"45.81","high":"47.98","low":"45.7","close":"47.87","volume":"57335"},{"date":"20100223","ticker":"HUM","open":"47.5","high":"47.73","low":"46.64","close":"46.82","volume":"24295"},{"date":"20100224","ticker":"HUM","open":"46.87","high":"46.95","low":"46","close":"46.91","volume":"21859"},{"date":"20100225","ticker":"HUM","open":"46.53","high":"47.59","low":"45.9","close":"47.13","volume":"20726"},{"date":"20100226","ticker":"HUM","open":"47.18","high":"48","low":"47","close":"47.33","volume":"19112"},{"date":"20100301","ticker":"HUM","open":"47.65","high":"48.47","low":"46.95","close":"47.48","volume":"22295"},{"date":"20100302","ticker":"HUM","open":"47.39","high":"47.945","low":"46.98","close":"47.49","volume":"14307"},{"date":"20100303","ticker":"HUM","open":"47.75","high":"48.13","low":"47.39","close":"47.49","volume":"15512"},{"date":"20100304","ticker":"HUM","open":"47.41","high":"47.49","low":"46.18","close":"47.12","volume":"20380"},{"date":"20100305","ticker":"HUM","open":"47.4","high":"48.14","low":"47.21","close":"48.14","volume":"16856"},{"date":"20100308","ticker":"HUM","open":"48.25","high":"48.25","low":"47.54","close":"47.95","volume":"14221"},{"date":"20100309","ticker":"HUM","open":"47.65","high":"48.19","low":"47.55","close":"47.94","volume":"12780"},{"date":"20100310","ticker":"HUM","open":"47.84","high":"48.65","low":"47.84","close":"48.32","volume":"13487"},{"date":"20100311","ticker":"HUM","open":"48.35","high":"49.17","low":"47.79","close":"49","volume":"14529"},{"date":"20100312","ticker":"HUM","open":"49.18","high":"49.18","low":"47.82","close":"47.97","volume":"21958"},{"date":"20100315","ticker":"HUM","open":"48.03","high":"48.05","low":"46.87","close":"47.5","volume":"16322"},{"date":"20100316","ticker":"HUM","open":"47.46","high":"47.75","low":"46.83","close":"47.7","volume":"11879"},{"date":"20100317","ticker":"HUM","open":"47.81","high":"48.35","low":"47.26","close":"48.23","volume":"20800"},{"date":"20100318","ticker":"HUM","open":"48.22","high":"50.25","low":"47.43","close":"50.09","volume":"48506"},{"date":"20100319","ticker":"HUM","open":"49.33","high":"50.84","low":"49.26","close":"50","volume":"36786"},{"date":"20100322","ticker":"HUM","open":"49.56","high":"50.63","low":"48.45","close":"49.32","volume":"39309"},{"date":"20100323","ticker":"HUM","open":"49.21","high":"49.5","low":"48.44","close":"49.02","volume":"13298"},{"date":"20100324","ticker":"HUM","open":"48.97","high":"48.98","low":"47.79","close":"47.9","volume":"21091"},{"date":"20100325","ticker":"HUM","open":"48.38","high":"48.42","low":"47.551","close":"47.87","volume":"17404"},{"date":"20100326","ticker":"HUM","open":"48.09","high":"48.09","low":"47.02","close":"47.2","volume":"16123"},{"date":"20100329","ticker":"HUM","open":"47.35","high":"47.71","low":"47.22","close":"47.43","volume":"19255"},{"date":"20100330","ticker":"HUM","open":"47.13","high":"47.41","low":"46.86","close":"47.34","volume":"19945"},{"date":"20100331","ticker":"HUM","open":"47.16","high":"47.32","low":"46.54","close":"46.77","volume":"18195"},{"date":"20100401","ticker":"HUM","open":"47.11","high":"47.25","low":"46.52","close":"46.92","volume":"12563"},{"date":"20100405","ticker":"HUM","open":"47.03","high":"47.27","low":"46.72","close":"47.11","volume":"11688"},{"date":"20100406","ticker":"HUM","open":"47.44","high":"48.44","low":"47.21","close":"47.83","volume":"38047"},{"date":"20100407","ticker":"HUM","open":"47.75","high":"47.75","low":"46.275","close":"46.49","volume":"23605"},{"date":"20100408","ticker":"HUM","open":"46.47","high":"46.48","low":"45.67","close":"46.31","volume":"17959"},{"date":"20100409","ticker":"HUM","open":"46.32","high":"46.36","low":"44.58","close":"45.13","volume":"34786"},{"date":"20100412","ticker":"HUM","open":"44.99","high":"45.155","low":"44.14","close":"44.51","volume":"30705"},{"date":"20100413","ticker":"HUM","open":"44.43","high":"44.62","low":"43.33","close":"44.08","volume":"37963"},{"date":"20100414","ticker":"HUM","open":"44.1","high":"44.42","low":"43.05","close":"44","volume":"27508"},{"date":"20100415","ticker":"HUM","open":"43.97","high":"44.31","low":"43.38","close":"44","volume":"25939"},{"date":"20100416","ticker":"HUM","open":"43.94","high":"44.6","low":"43.31","close":"43.93","volume":"30012"},{"date":"20100419","ticker":"HUM","open":"43.67","high":"45.45","low":"43.66","close":"44.66","volume":"28258"},{"date":"20100420","ticker":"HUM","open":"45.48","high":"45.64","low":"44.27","close":"45.17","volume":"27958"},{"date":"20100421","ticker":"HUM","open":"45.04","high":"45.47","low":"44.19","close":"44.45","volume":"20660"},{"date":"20100422","ticker":"HUM","open":"44.38","high":"44.5","low":"43.65","close":"44.48","volume":"22667"},{"date":"20100423","ticker":"HUM","open":"44.38","high":"45.83","low":"44.07","close":"45.53","volume":"43829"},{"date":"20100426","ticker":"HUM","open":"46.92","high":"46.92","low":"43.42","close":"43.56","volume":"56507"},{"date":"20100427","ticker":"HUM","open":"43.31","high":"44.84","low":"43.21","close":"43.57","volume":"41950"},{"date":"20100428","ticker":"HUM","open":"43.58","high":"46.08","low":"43.41","close":"45.69","volume":"42607"},{"date":"20100429","ticker":"HUM","open":"46.17","high":"47.61","low":"46.08","close":"47.19","volume":"32187"},{"date":"20100430","ticker":"HUM","open":"47.17","high":"47.32","low":"45.64","close":"45.72","volume":"35766"},{"date":"20100503","ticker":"HUM","open":"45.81","high":"46.42","low":"45.15","close":"46.36","volume":"25963"},{"date":"20100504","ticker":"HUM","open":"45.69","high":"46.12","low":"45.34","close":"45.85","volume":"31808"},{"date":"20100505","ticker":"HUM","open":"45.4","high":"46.62","low":"45.39","close":"46.57","volume":"29763"},{"date":"20100506","ticker":"HUM","open":"46.49","high":"47.12","low":"43.27","close":"45.59","volume":"37115"},{"date":"20100507","ticker":"HUM","open":"45.35","high":"45.35","low":"43.66","close":"44.35","volume":"26378"},{"date":"20100510","ticker":"HUM","open":"45.59","high":"46.33","low":"45.26","close":"45.95","volume":"22470"},{"date":"20100511","ticker":"HUM","open":"45.47","high":"46.24","low":"45.37","close":"45.6","volume":"22943"},{"date":"20100512","ticker":"HUM","open":"45.65","high":"46.27","low":"45.64","close":"45.99","volume":"38927"},{"date":"20100513","ticker":"HUM","open":"45.56","high":"46.69","low":"45.5","close":"45.8","volume":"22390"},{"date":"20100514","ticker":"HUM","open":"45.58","high":"45.83","low":"44.79","close":"45.75","volume":"16892"},{"date":"20100517","ticker":"HUM","open":"45.71","high":"46.27","low":"44.98","close":"45.89","volume":"24000"},{"date":"20100518","ticker":"HUM","open":"46.09","high":"47.21","low":"45.98","close":"46.2","volume":"26272"},{"date":"20100519","ticker":"HUM","open":"46.09","high":"46.65","low":"45.66","close":"46.24","volume":"19110"},{"date":"20100520","ticker":"HUM","open":"45.39","high":"45.72","low":"44.26","close":"44.34","volume":"19364"},{"date":"20100521","ticker":"HUM","open":"43.58","high":"44.88","low":"43.17","close":"44.71","volume":"24255"},{"date":"20100524","ticker":"HUM","open":"44.44","high":"45.42","low":"44","close":"44.81","volume":"16711"},{"date":"20100525","ticker":"HUM","open":"43.86","high":"44.22","low":"43.3","close":"44.21","volume":"19742"},{"date":"20100526","ticker":"HUM","open":"44.4","high":"45.53","low":"44.2901","close":"44.54","volume":"18668"},{"date":"20100527","ticker":"HUM","open":"45.57","high":"45.74","low":"44.98","close":"45.71","volume":"11051"},{"date":"20100528","ticker":"HUM","open":"45.62","high":"46.39","low":"45.24","close":"46.05","volume":"18455"},{"date":"20100601","ticker":"HUM","open":"45.62","high":"46.72","low":"45.36","close":"45.52","volume":"12482"},{"date":"20100602","ticker":"HUM","open":"45.65","high":"47.43","low":"45.53","close":"47.43","volume":"17318"},{"date":"20100603","ticker":"HUM","open":"47.52","high":"48.4","low":"47.32","close":"48.23","volume":"13876"},{"date":"20100604","ticker":"HUM","open":"47.38","high":"49.27","low":"47.22","close":"47.39","volume":"34478"},{"date":"20100607","ticker":"HUM","open":"47.65","high":"48.2","low":"45.74","close":"46.59","volume":"34739"},{"date":"20100608","ticker":"HUM","open":"46.64","high":"47.14","low":"45.91","close":"46.63","volume":"17834"},{"date":"20100609","ticker":"HUM","open":"46.9","high":"47.47","low":"46.6","close":"46.84","volume":"21542"},{"date":"20100610","ticker":"HUM","open":"47.22","high":"47.4","low":"46.52","close":"47.27","volume":"16872"},{"date":"20100611","ticker":"HUM","open":"46.9","high":"47.95","low":"46.3201","close":"47.95","volume":"17175"},{"date":"20100614","ticker":"HUM","open":"48.22","high":"48.67","low":"48.04","close":"48.1","volume":"12313"},{"date":"20100615","ticker":"HUM","open":"48.25","high":"48.98","low":"48.06","close":"48.98","volume":"15884"},{"date":"20100616","ticker":"HUM","open":"48.59","high":"49.11","low":"48.4901","close":"48.83","volume":"25341"},{"date":"20100617","ticker":"HUM","open":"49.01","high":"49.49","low":"48.83","close":"49.49","volume":"18738"},{"date":"20100618","ticker":"HUM","open":"49.29","high":"49.57","low":"48.83","close":"49.25","volume":"15590"},{"date":"20100621","ticker":"HUM","open":"49.79","high":"50.16","low":"49.03","close":"49.26","volume":"13730"},{"date":"20100622","ticker":"HUM","open":"49.22","high":"49.59","low":"48.34","close":"48.41","volume":"15805"},{"date":"20100623","ticker":"HUM","open":"48.15","high":"49.0254","low":"47.67","close":"48.64","volume":"19128"},{"date":"20100624","ticker":"HUM","open":"48.57","high":"49.03","low":"47.78","close":"47.92","volume":"12693"},{"date":"20100625","ticker":"HUM","open":"48.06","high":"48.47","low":"47.51","close":"48.1","volume":"25433"},{"date":"20100628","ticker":"HUM","open":"48.15","high":"48.39","low":"47.62","close":"48.06","volume":"11824"},{"date":"20100629","ticker":"HUM","open":"47.12","high":"47.49","low":"45.73","close":"45.97","volume":"18978"},{"date":"20100630","ticker":"HUM","open":"45.86","high":"46.34","low":"45.54","close":"45.67","volume":"18289"},{"date":"20100701","ticker":"HUM","open":"45.54","high":"45.54","low":"43.59","close":"44.59","volume":"23179"},{"date":"20100702","ticker":"HUM","open":"44.56","high":"44.81","low":"44.01","close":"44.34","volume":"12836"},{"date":"20100706","ticker":"HUM","open":"44.86","high":"45.24","low":"43.97","close":"44.46","volume":"15166"},{"date":"20100707","ticker":"HUM","open":"44.62","high":"45.5","low":"44.38","close":"45.39","volume":"19270"},{"date":"20100708","ticker":"HUM","open":"45.79","high":"46.35","low":"45.59","close":"45.94","volume":"13980"},{"date":"20100709","ticker":"HUM","open":"46.22","high":"46.28","low":"45.65","close":"46.2","volume":"12665"},{"date":"20100712","ticker":"HUM","open":"46.05","high":"46.14","low":"45.5709","close":"45.92","volume":"17073"},{"date":"20100713","ticker":"HUM","open":"46.27","high":"46.61","low":"45.86","close":"46.36","volume":"14602"},{"date":"20100714","ticker":"HUM","open":"46.14","high":"46.93","low":"45.81","close":"46.88","volume":"12395"},{"date":"20100715","ticker":"HUM","open":"46.81","high":"47.47","low":"46.52","close":"46.85","volume":"20938"},{"date":"20100716","ticker":"HUM","open":"46.5","high":"47.09","low":"45.55","close":"45.66","volume":"16898"},{"date":"20100719","ticker":"HUM","open":"45.86","high":"46.87","low":"45.76","close":"46.52","volume":"15270"},{"date":"20100720","ticker":"HUM","open":"46.47","high":"46.94","low":"45.5551","close":"46.5","volume":"19283"},{"date":"20100721","ticker":"HUM","open":"46.49","high":"46.71","low":"45.42","close":"45.71","volume":"13300"},{"date":"20100722","ticker":"HUM","open":"46.3","high":"47.07","low":"46.04","close":"46.33","volume":"12835"},{"date":"20100723","ticker":"HUM","open":"46.23","high":"46.49","low":"45.48","close":"46.02","volume":"14608"},{"date":"20100726","ticker":"HUM","open":"46.05","high":"46.92","low":"46.05","close":"46.91","volume":"8844"},{"date":"20100727","ticker":"HUM","open":"47.19","high":"47.29","low":"46.57","close":"46.63","volume":"9849"},{"date":"20100728","ticker":"HUM","open":"46.5","high":"46.69","low":"45.56","close":"45.74","volume":"15699"},{"date":"20100729","ticker":"HUM","open":"46.08","high":"46.61","low":"45.36","close":"46.17","volume":"19623"},{"date":"20100730","ticker":"HUM","open":"45.87","high":"47.87","low":"45.66","close":"47.02","volume":"33530"},{"date":"20100802","ticker":"HUM","open":"48.83","high":"48.83","low":"47.31","close":"48.73","volume":"30840"},{"date":"20100803","ticker":"HUM","open":"48.66","high":"49.4885","low":"48.27","close":"48.89","volume":"17792"},{"date":"20100804","ticker":"HUM","open":"48.94","high":"49.76","low":"48.91","close":"49.72","volume":"15099"},{"date":"20100805","ticker":"HUM","open":"49.56","high":"50.38","low":"49.35","close":"49.97","volume":"23945"},{"date":"20100806","ticker":"HUM","open":"49.61","high":"50.78","low":"49.53","close":"50.61","volume":"16609"},{"date":"20100809","ticker":"HUM","open":"50.99","high":"51.24","low":"50.53","close":"50.71","volume":"12577"},{"date":"20100810","ticker":"HUM","open":"50.18","high":"50.95","low":"49.77","close":"50.68","volume":"16800"},{"date":"20100811","ticker":"HUM","open":"49.96","high":"49.96","low":"48.211","close":"48.93","volume":"27890"},{"date":"20100812","ticker":"HUM","open":"48.08","high":"49.52","low":"48","close":"49.31","volume":"23392"},{"date":"20100813","ticker":"HUM","open":"49.12","high":"49.53","low":"48.57","close":"49.33","volume":"11600"},{"date":"20100816","ticker":"HUM","open":"49.04","high":"49.14","low":"48.52","close":"49","volume":"10153"},{"date":"20100817","ticker":"HUM","open":"49.46","high":"50.07","low":"49.12","close":"49.67","volume":"16939"},{"date":"20100819","ticker":"HUM","open":"50.13","high":"50.13","low":"48.735","close":"48.81","volume":"14326"},{"date":"20100820","ticker":"HUM","open":"45.97","high":"48.73","low":"47.92","close":"48.51","volume":"19082"}]