[{"date":"20090821","ticker":"NKE","open":"55.99","high":"56.5","low":"55.24","close":"55.65","volume":"56393"},{"date":"20090824","ticker":"NKE","open":"55.7","high":"56.25","low":"55.56","close":"56","volume":"38094"},{"date":"20090825","ticker":"NKE","open":"56.29","high":"56.47","low":"55.1","close":"55.16","volume":"45812"},{"date":"20090826","ticker":"NKE","open":"55.28","high":"56","low":"54.93","close":"55.45","volume":"33498"},{"date":"20090827","ticker":"NKE","open":"55.54","high":"57.13","low":"54.8","close":"56.83","volume":"47704"},{"date":"20090828","ticker":"NKE","open":"57.05","high":"57.38","low":"55.81","close":"56.18","volume":"21445"},{"date":"20090831","ticker":"NKE","open":"55.92","high":"56","low":"55.15","close":"55.39","volume":"18386"},{"date":"20090901","ticker":"NKE","open":"54.905","high":"55.52","low":"54.11","close":"54.36","volume":"50405"},{"date":"20090902","ticker":"NKE","open":"54.12","high":"54.33","low":"53.22","close":"53.31","volume":"43852"},{"date":"20090903","ticker":"NKE","open":"53.49","high":"53.9","low":"53.31","close":"53.73","volume":"35215"},{"date":"20090904","ticker":"NKE","open":"53.87","high":"54.38","low":"53.42","close":"54.23","volume":"24264"},{"date":"20090909","ticker":"NKE","open":"54.93","high":"55.48","low":"54.53","close":"55.35","volume":"39960"},{"date":"20090910","ticker":"NKE","open":"55.35","high":"55.8","low":"54.87","close":"55.42","volume":"46632"},{"date":"20090911","ticker":"NKE","open":"55.56","high":"55.89","low":"54.76","close":"54.99","volume":"43420"},{"date":"20090914","ticker":"NKE","open":"54.48","high":"55.22","low":"53.52","close":"54.91","volume":"35747"},{"date":"20090915","ticker":"NKE","open":"54.76","high":"55","low":"53.97","close":"54.69","volume":"37046"},{"date":"20090916","ticker":"NKE","open":"54.76","high":"57.45","low":"54.41","close":"57.18","volume":"60866"},{"date":"20090917","ticker":"NKE","open":"57","high":"58.81","low":"56.87","close":"58.09","volume":"36905"},{"date":"20090918","ticker":"NKE","open":"58.25","high":"58.88","low":"57.95","close":"58.59","volume":"28813"},{"date":"20090921","ticker":"NKE","open":"58.05","high":"59.37","low":"57.66","close":"58.55","volume":"23681"},{"date":"20090922","ticker":"NKE","open":"58.97","high":"59.5","low":"58.44","close":"58.57","volume":"30935"},{"date":"20090923","ticker":"NKE","open":"58.8","high":"59.25","low":"58.23","close":"58.3","volume":"108930"},{"date":"20090924","ticker":"NKE","open":"58.31","high":"58.74","low":"57.83","close":"58.17","volume":"65553"},{"date":"20090925","ticker":"NKE","open":"58.33","high":"59.85","low":"58.3","close":"58.64","volume":"43736"},{"date":"20090928","ticker":"NKE","open":"58.63","high":"59.31","low":"58.46","close":"59","volume":"25266"},{"date":"20090929","ticker":"NKE","open":"59.23","high":"60.19","low":"59.12","close":"60.09","volume":"86908"},{"date":"20090930","ticker":"NKE","open":"64.01","high":"64.95","low":"64.01","close":"64.7","volume":"167937"},{"date":"20091001","ticker":"NKE","open":"64","high":"64.4","low":"62.5","close":"62.5","volume":"82590"},{"date":"20091002","ticker":"NKE","open":"61.53","high":"62.39","low":"61.08","close":"62.02","volume":"56420"},{"date":"20091005","ticker":"NKE","open":"61.88","high":"62.92","low":"61.75","close":"62.78","volume":"29682"},{"date":"20091006","ticker":"NKE","open":"62.91","high":"64.42","low":"62.84","close":"63.09","volume":"36514"},{"date":"20091007","ticker":"NKE","open":"62.94","high":"63.725","low":"62.8","close":"63.42","volume":"21906"},{"date":"20091008","ticker":"NKE","open":"63.71","high":"64.36","low":"63.55","close":"64.02","volume":"23412"},{"date":"20091009","ticker":"NKE","open":"64.12","high":"64.19","low":"63","close":"63.59","volume":"22174"},{"date":"20091012","ticker":"NKE","open":"63.85","high":"64","low":"63.23","close":"63.25","volume":"15500"},{"date":"20091013","ticker":"NKE","open":"63.26","high":"63.85","low":"63.01","close":"63.68","volume":"17655"},{"date":"20091014","ticker":"NKE","open":"64.08","high":"65.23","low":"63.91","close":"64.9","volume":"36579"},{"date":"20091015","ticker":"NKE","open":"64.73","high":"65.01","low":"64.13","close":"64.96","volume":"36618"},{"date":"20091016","ticker":"NKE","open":"64.34","high":"65.2","low":"64.26","close":"65.1","volume":"36542"},{"date":"20091019","ticker":"NKE","open":"65.04","high":"66.35","low":"64.41","close":"66.09","volume":"46283"},{"date":"20091020","ticker":"NKE","open":"65.53","high":"65.79","low":"64.65","close":"65.09","volume":"33899"},{"date":"20091021","ticker":"NKE","open":"65.1","high":"65.8","low":"64.7","close":"64.75","volume":"33283"},{"date":"20091022","ticker":"NKE","open":"64.82","high":"65.7","low":"64.4","close":"65.19","volume":"24977"},{"date":"20091023","ticker":"NKE","open":"65.05","high":"65.16","low":"63.55","close":"64.17","volume":"31745"},{"date":"20091026","ticker":"NKE","open":"64.08","high":"64.96","low":"63.59","close":"63.75","volume":"29535"},{"date":"20091027","ticker":"NKE","open":"63.65","high":"64.69","low":"62.5","close":"64.09","volume":"39279"},{"date":"20091028","ticker":"NKE","open":"63.83","high":"64.26","low":"62.28","close":"62.57","volume":"37051"},{"date":"20091105","ticker":"NKE","open":"63.49","high":"64.79","low":"63.07","close":"64.76","volume":"26445"},{"date":"20091106","ticker":"NKE","open":"64.65","high":"64.82","low":"63.88","close":"64.56","volume":"19088"},{"date":"20091109","ticker":"NKE","open":"64.5","high":"65.33","low":"64.36","close":"65.32","volume":"22867"},{"date":"20091110","ticker":"NKE","open":"65.34","high":"65.69","low":"64","close":"64.47","volume":"24745"},{"date":"20091111","ticker":"NKE","open":"64.61","high":"65.57","low":"64.57","close":"64.93","volume":"16701"},{"date":"20091112","ticker":"NKE","open":"64.94","high":"65.39","low":"63.81","close":"64.09","volume":"16522"},{"date":"20091113","ticker":"NKE","open":"64.27","high":"64.96","low":"63.72","close":"64.42","volume":"18277"},{"date":"20091116","ticker":"NKE","open":"64.66","high":"66.34","low":"64.52","close":"66.1","volume":"25950"},{"date":"20091117","ticker":"NKE","open":"65.89","high":"66","low":"64.43","close":"64.96","volume":"19635"},{"date":"20091118","ticker":"NKE","open":"64.79","high":"64.79","low":"63.79","close":"64.42","volume":"20245"},{"date":"20091119","ticker":"NKE","open":"63.93","high":"64.3","low":"62.88","close":"63.56","volume":"24632"},{"date":"20091120","ticker":"NKE","open":"63.34","high":"64.08","low":"62.7","close":"63.92","volume":"31536"},{"date":"20091123","ticker":"NKE","open":"64.82","high":"65.53","low":"64.04","close":"64.49","volume":"23580"},{"date":"20091124","ticker":"NKE","open":"64.68","high":"65.1","low":"64.32","close":"64.52","volume":"16122"},{"date":"20091125","ticker":"NKE","open":"64.53","high":"65.87","low":"64.53","close":"65.7","volume":"19965"},{"date":"20091127","ticker":"NKE","open":"64.52","high":"65.44","low":"64","close":"65.05","volume":"11747"},{"date":"20091130","ticker":"NKE","open":"64.8","high":"65.54","low":"64.39","close":"64.89","volume":"23152"},{"date":"20091201","ticker":"NKE","open":"65.27","high":"66.09","low":"64.74","close":"65.4","volume":"19876"},{"date":"20091202","ticker":"NKE","open":"64.53","high":"66.13","low":"64.53","close":"65.35","volume":"14842"},{"date":"20091203","ticker":"NKE","open":"65.26","high":"65.59","low":"64.54","close":"64.67","volume":"27587"},{"date":"20091204","ticker":"NKE","open":"65.28","high":"65.85","low":"63.82","close":"64.3","volume":"25450"},{"date":"20091207","ticker":"NKE","open":"64.3","high":"64.99","low":"64.3","close":"64.54","volume":"22370"},{"date":"20091208","ticker":"NKE","open":"64","high":"64.39","low":"63.38","close":"63.53","volume":"36277"},{"date":"20091209","ticker":"NKE","open":"63.51","high":"63.51","low":"61.75","close":"61.95","volume":"58595"},{"date":"20091210","ticker":"NKE","open":"62.2","high":"63.4","low":"62.2","close":"62.7","volume":"29931"},{"date":"20091211","ticker":"NKE","open":"63.44","high":"64.19","low":"63.09","close":"63.86","volume":"27150"},{"date":"20091214","ticker":"NKE","open":"64.01","high":"64.32","low":"63.12","close":"64.16","volume":"23144"},{"date":"20091215","ticker":"NKE","open":"63.93","high":"65.09","low":"63.62","close":"64.35","volume":"24012"},{"date":"20091216","ticker":"NKE","open":"64.68","high":"64.68","low":"63.63","close":"64.05","volume":"19099"},{"date":"20091217","ticker":"NKE","open":"63.57","high":"64.05","low":"63.07","close":"63.25","volume":"29199"},{"date":"20091218","ticker":"NKE","open":"64.4","high":"65.35","low":"64.05","close":"64.42","volume":"50808"},{"date":"20091221","ticker":"NKE","open":"64.52","high":"65.27","low":"64.45","close":"64.88","volume":"18498"},{"date":"20091222","ticker":"NKE","open":"64.88","high":"65.33","low":"64.18","close":"65.1","volume":"20597"},{"date":"20091223","ticker":"NKE","open":"65.07","high":"65.53","low":"64.89","close":"65.44","volume":"15371"},{"date":"20091224","ticker":"NKE","open":"65.44","high":"65.56","low":"65","close":"65.25","volume":"5755"},{"date":"20091228","ticker":"NKE","open":"65.25","high":"65.55","low":"64.78","close":"65.5","volume":"14120"},{"date":"20091229","ticker":"NKE","open":"65.5","high":"66.43","low":"65.22","close":"66.21","volume":"20208"},{"date":"20091230","ticker":"NKE","open":"65.85","high":"66.24","low":"65.71","close":"66.14","volume":"17330"},{"date":"20091231","ticker":"NKE","open":"66.21","high":"66.62","low":"66.05","close":"66.07","volume":"15869"},{"date":"20100104","ticker":"NKE","open":"66.06","high":"66.07","low":"65.12","close":"65.35","volume":"29931"},{"date":"20100105","ticker":"NKE","open":"65.14","high":"65.79","low":"64.7","close":"65.61","volume":"15688"},{"date":"20100106","ticker":"NKE","open":"65.4","high":"65.69","low":"64.94","close":"65.21","volume":"33498"},{"date":"20100107","ticker":"NKE","open":"65.12","high":"66","low":"65.05","close":"65.85","volume":"17969"},{"date":"20100108","ticker":"NKE","open":"65.79","high":"65.85","low":"64.94","close":"65.72","volume":"18124"},{"date":"20100111","ticker":"NKE","open":"65.92","high":"65.93","low":"64.65","close":"64.91","volume":"26695"},{"date":"20100112","ticker":"NKE","open":"64.6","high":"65.1","low":"64.28","close":"64.82","volume":"28714"},{"date":"20100113","ticker":"NKE","open":"65.11","high":"65.67","low":"64.78","close":"65.4","volume":"14122"},{"date":"20100114","ticker":"NKE","open":"65.49","high":"65.83","low":"64.75","close":"64.99","volume":"18279"},{"date":"20100115","ticker":"NKE","open":"64.78","high":"65.01","low":"63.95","close":"64.39","volume":"28233"},{"date":"20100119","ticker":"NKE","open":"64.2","high":"64.8","low":"63.96","close":"64.71","volume":"18633"},{"date":"20100120","ticker":"NKE","open":"64.21","high":"64.41","low":"63.57","close":"64.18","volume":"20021"},{"date":"20100121","ticker":"NKE","open":"64.31","high":"64.34","low":"63.03","close":"63.64","volume":"34958"},{"date":"20100122","ticker":"NKE","open":"63.51","high":"64.24","low":"62.95","close":"62.98","volume":"33300"},{"date":"20100125","ticker":"NKE","open":"63.37","high":"64.04","low":"63.31","close":"63.67","volume":"26874"},{"date":"20100126","ticker":"NKE","open":"63.33","high":"64.11","low":"63.05","close":"63.74","volume":"16778"},{"date":"20100127","ticker":"NKE","open":"63.67","high":"64.17","low":"63.25","close":"64","volume":"33901"},{"date":"20100128","ticker":"NKE","open":"64.25","high":"65","low":"63.37","close":"63.52","volume":"17895"},{"date":"20100129","ticker":"NKE","open":"63.64","high":"64.65","low":"63.55","close":"63.75","volume":"26006"},{"date":"20100201","ticker":"NKE","open":"63.97","high":"64.45","low":"63.51","close":"64.1","volume":"16019"},{"date":"20100202","ticker":"NKE","open":"64.29","high":"64.29","low":"63.61","close":"63.93","volume":"23848"},{"date":"20100203","ticker":"NKE","open":"63.69","high":"64.1","low":"63.32","close":"64","volume":"19723"},{"date":"20100204","ticker":"NKE","open":"63.53","high":"63.75","low":"62.05","close":"62.09","volume":"44812"},{"date":"20100205","ticker":"NKE","open":"62.02","high":"62.23","low":"60.89","close":"61.7","volume":"32777"},{"date":"20100208","ticker":"NKE","open":"61.62","high":"62.12","low":"61.23","close":"61.3","volume":"20443"},{"date":"20100209","ticker":"NKE","open":"61.78","high":"63.1","low":"61.67","close":"62.51","volume":"23595"},{"date":"20100210","ticker":"NKE","open":"62.51","high":"62.95","low":"62.25","close":"62.64","volume":"19246"},{"date":"20100211","ticker":"NKE","open":"62.43","high":"63.17","low":"62.12","close":"62.95","volume":"17525"},{"date":"20100212","ticker":"NKE","open":"62.52","high":"62.55","low":"61.72","close":"62.49","volume":"27880"},{"date":"20100216","ticker":"NKE","open":"62.82","high":"63.65","low":"62.33","close":"63.65","volume":"24070"},{"date":"20100217","ticker":"NKE","open":"63.87","high":"64.69","low":"63.62","close":"64.48","volume":"26601"},{"date":"20100218","ticker":"NKE","open":"64.49","high":"64.59","low":"63.91","close":"64.44","volume":"16170"},{"date":"20100219","ticker":"NKE","open":"64.14","high":"64.6","low":"64.01","close":"64.35","volume":"23745"},{"date":"20100222","ticker":"NKE","open":"64.57","high":"64.77","low":"64.03","close":"64.31","volume":"17162"},{"date":"20100223","ticker":"NKE","open":"64.3","high":"64.55","low":"63.61","close":"64.13","volume":"19347"},{"date":"20100224","ticker":"NKE","open":"64.3","high":"65.02","low":"64","close":"64.93","volume":"29045"},{"date":"20100225","ticker":"NKE","open":"65.01","high":"66.28","low":"64.01","close":"66.16","volume":"39919"},{"date":"20100226","ticker":"NKE","open":"66.23","high":"67.85","low":"66.23","close":"67.6","volume":"49083"},{"date":"20100301","ticker":"NKE","open":"67.91","high":"68.71","low":"67.61","close":"68.24","volume":"26685"},{"date":"20100302","ticker":"NKE","open":"68.06","high":"68.33","low":"67.68","close":"68.03","volume":"24612"},{"date":"20100303","ticker":"NKE","open":"67.7","high":"67.97","low":"67.26","close":"67.64","volume":"21676"},{"date":"20100304","ticker":"NKE","open":"68.02","high":"68.06","low":"67.44","close":"67.63","volume":"15766"},{"date":"20100305","ticker":"NKE","open":"67.83","high":"68.51","low":"67.83","close":"68.32","volume":"18650"},{"date":"20100308","ticker":"NKE","open":"67.97","high":"68.96","low":"67.97","close":"68.82","volume":"17710"},{"date":"20100309","ticker":"NKE","open":"68.76","high":"69.18","low":"68.53","close":"68.93","volume":"15106"},{"date":"20100310","ticker":"NKE","open":"68.77","high":"69.25","low":"68.41","close":"69.12","volume":"13982"},{"date":"20100311","ticker":"NKE","open":"69.1","high":"69.85","low":"68.71","close":"69.75","volume":"17400"},{"date":"20100312","ticker":"NKE","open":"69.42","high":"69.99","low":"69.41","close":"69.9","volume":"18021"},{"date":"20100315","ticker":"NKE","open":"69.75","high":"70.73","low":"69.72","close":"70.39","volume":"23785"},{"date":"20100316","ticker":"NKE","open":"70.33","high":"71.05","low":"70.1","close":"70.38","volume":"25268"},{"date":"20100317","ticker":"NKE","open":"70.5","high":"71.33","low":"70.28","close":"70.88","volume":"36879"},{"date":"20100318","ticker":"NKE","open":"73.35","high":"75.35","low":"73.3","close":"74.66","volume":"109240"},{"date":"20100319","ticker":"NKE","open":"74.26","high":"74.32","low":"73.12","close":"73.52","volume":"46974"},{"date":"20100322","ticker":"NKE","open":"72.89","high":"74.16","low":"72.82","close":"73.88","volume":"29240"},{"date":"20100323","ticker":"NKE","open":"74.4","high":"74.59","low":"73.97","close":"74.49","volume":"22465"},{"date":"20100324","ticker":"NKE","open":"74.35","high":"74.39","low":"73.01","close":"73.38","volume":"27673"},{"date":"20100325","ticker":"NKE","open":"74.17","high":"74.78","low":"73.53","close":"73.57","volume":"28304"},{"date":"20100326","ticker":"NKE","open":"73.8","high":"74.75","low":"73.37","close":"73.89","volume":"21654"},{"date":"20100329","ticker":"NKE","open":"74.16","high":"74.33","low":"73.58","close":"73.97","volume":"16306"},{"date":"20100330","ticker":"NKE","open":"74.01","high":"74.4","low":"73.55","close":"73.81","volume":"16153"},{"date":"20100331","ticker":"NKE","open":"73.49","high":"74.1","low":"73.2802","close":"73.5","volume":"19790"},{"date":"20100401","ticker":"NKE","open":"73.96","high":"74.39","low":"73.75","close":"74.01","volume":"20941"},{"date":"20100405","ticker":"NKE","open":"74.19","high":"74.82","low":"73.62","close":"74.11","volume":"17704"},{"date":"20100406","ticker":"NKE","open":"73.54","high":"74.15","low":"73.5","close":"73.91","volume":"21070"},{"date":"20100407","ticker":"NKE","open":"73.97","high":"74.1884","low":"73.3","close":"73.59","volume":"22128"},{"date":"20100408","ticker":"NKE","open":"73.46","high":"74.28","low":"73.06","close":"73.99","volume":"26026"},{"date":"20100409","ticker":"NKE","open":"74.18","high":"75.28","low":"73.65","close":"75.18","volume":"31255"},{"date":"20100412","ticker":"NKE","open":"75.29","high":"75.95","low":"75.2","close":"75.53","volume":"22168"},{"date":"20100413","ticker":"NKE","open":"75.43","high":"75.93","low":"74.75","close":"75.51","volume":"17563"},{"date":"20100414","ticker":"NKE","open":"75.61","high":"75.86","low":"75","close":"75.8","volume":"17011"},{"date":"20100415","ticker":"NKE","open":"75.57","high":"75.82","low":"74.9701","close":"75.64","volume":"17536"},{"date":"20100416","ticker":"NKE","open":"75.59","high":"76","low":"74.98","close":"75.17","volume":"34348"},{"date":"20100419","ticker":"NKE","open":"74.95","high":"75.8","low":"74.25","close":"75.58","volume":"21976"},{"date":"20100420","ticker":"NKE","open":"76.02","high":"76.58","low":"75.9","close":"76.36","volume":"23961"},{"date":"20100421","ticker":"NKE","open":"76.4","high":"77.139","low":"76.17","close":"76.72","volume":"27002"},{"date":"20100422","ticker":"NKE","open":"76.29","high":"78.525","low":"76.21","close":"78.23","volume":"34622"},{"date":"20100423","ticker":"NKE","open":"77.82","high":"78.44","low":"77.3","close":"77.9","volume":"25378"},{"date":"20100426","ticker":"NKE","open":"77.91","high":"78.47","low":"77.78","close":"78.02","volume":"15126"},{"date":"20100427","ticker":"NKE","open":"77.67","high":"78.49","low":"76.61","close":"76.74","volume":"27542"},{"date":"20100428","ticker":"NKE","open":"76.94","high":"78.03","low":"76.14","close":"76.44","volume":"27030"},{"date":"20100429","ticker":"NKE","open":"77.1","high":"77.69","low":"76.72","close":"77.57","volume":"22709"},{"date":"20100430","ticker":"NKE","open":"77.45","high":"77.88","low":"75.89","close":"75.91","volume":"24674"},{"date":"20100503","ticker":"NKE","open":"76.01","high":"78.39","low":"75.91","close":"77.77","volume":"21071"},{"date":"20100504","ticker":"NKE","open":"78.02","high":"78.55","low":"77.1","close":"77.35","volume":"36326"},{"date":"20100505","ticker":"NKE","open":"76.87","high":"77.2999","low":"74.7","close":"75.21","volume":"43276"},{"date":"20100506","ticker":"NKE","open":"74.55","high":"75.99","low":"66.99","close":"72.3","volume":"65825"},{"date":"20100507","ticker":"NKE","open":"71.35","high":"72.44","low":"69.7752","close":"70.61","volume":"53756"},{"date":"20100510","ticker":"NKE","open":"73.89","high":"76.77","low":"73.74","close":"76.65","volume":"66194"},{"date":"20100511","ticker":"NKE","open":"75.86","high":"77.07","low":"75.76","close":"76.43","volume":"34388"},{"date":"20100512","ticker":"NKE","open":"76.71","high":"77.98","low":"76.01","close":"77.85","volume":"24890"},{"date":"20100513","ticker":"NKE","open":"77.65","high":"77.99","low":"75.35","close":"75.55","volume":"52442"},{"date":"20100514","ticker":"NKE","open":"74.63","high":"75","low":"73.18","close":"73.74","volume":"47535"},{"date":"20100517","ticker":"NKE","open":"73.73","high":"73.85","low":"72.03","close":"73.63","volume":"42361"},{"date":"20100518","ticker":"NKE","open":"74.16","high":"75.01","low":"72.7","close":"72.93","volume":"47139"},{"date":"20100519","ticker":"NKE","open":"72.54","high":"72.72","low":"71","close":"72.25","volume":"58697"},{"date":"20100520","ticker":"NKE","open":"70.53","high":"71.59","low":"69.57","close":"70.31","volume":"62641"},{"date":"20100521","ticker":"NKE","open":"68.9","high":"71.78","low":"68.14","close":"71.39","volume":"42660"},{"date":"20100524","ticker":"NKE","open":"71.17","high":"71.91","low":"70.7101","close":"71.34","volume":"56672"},{"date":"20100525","ticker":"NKE","open":"70.09","high":"73","low":"69.27","close":"72.91","volume":"52910"},{"date":"20100526","ticker":"NKE","open":"73.05","high":"73.62","low":"71.92","close":"72.52","volume":"41818"},{"date":"20100527","ticker":"NKE","open":"73.28","high":"73.96","low":"72.76","close":"73.9","volume":"36859"},{"date":"20100528","ticker":"NKE","open":"73.62","high":"73.86","low":"71.96","close":"72.38","volume":"38892"},{"date":"20100601","ticker":"NKE","open":"71.315","high":"72.62","low":"70.7","close":"71.18","volume":"36710"},{"date":"20100602","ticker":"NKE","open":"71.31","high":"73.06","low":"71.31","close":"73","volume":"31652"},{"date":"20100603","ticker":"NKE","open":"73.2","high":"73.86","low":"72.94","close":"73.63","volume":"28392"},{"date":"20100604","ticker":"NKE","open":"72.36","high":"72.47","low":"70.16","close":"70.77","volume":"38509"},{"date":"20100607","ticker":"NKE","open":"70.54","high":"71.02","low":"69.48","close":"69.59","volume":"27641"},{"date":"20100608","ticker":"NKE","open":"69.59","high":"70.43","low":"68.65","close":"70.26","volume":"30658"},{"date":"20100609","ticker":"NKE","open":"70.52","high":"71.33","low":"69.67","close":"70.01","volume":"32285"},{"date":"20100610","ticker":"NKE","open":"71.19","high":"72.55","low":"71.14","close":"71.75","volume":"29578"},{"date":"20100611","ticker":"NKE","open":"71.29","high":"72.64","low":"71.03","close":"72.33","volume":"22021"},{"date":"20100614","ticker":"NKE","open":"72.49","high":"72.95","low":"71.91","close":"72.22","volume":"21866"},{"date":"20100615","ticker":"NKE","open":"72.29","high":"73.98","low":"72.29","close":"73.98","volume":"21744"},{"date":"20100616","ticker":"NKE","open":"73.37","high":"74.5","low":"73.08","close":"73.83","volume":"31751"},{"date":"20100617","ticker":"NKE","open":"74.27","high":"74.7","low":"73.63","close":"74.57","volume":"29506"},{"date":"20100618","ticker":"NKE","open":"74.8","high":"75.23","low":"74.47","close":"74.94","volume":"27991"},{"date":"20100621","ticker":"NKE","open":"75.49","high":"75.92","low":"73.82","close":"74.35","volume":"27980"},{"date":"20100622","ticker":"NKE","open":"74.44","high":"75","low":"72.17","close":"72.46","volume":"25970"},{"date":"20100623","ticker":"NKE","open":"72.66","high":"73.177","low":"71.5","close":"72.52","volume":"29147"},{"date":"20100624","ticker":"NKE","open":"70.01","high":"70.67","low":"69.2","close":"69.63","volume":"90260"},{"date":"20100625","ticker":"NKE","open":"69.86","high":"70.47","low":"68.9","close":"70.12","volume":"45225"},{"date":"20100628","ticker":"NKE","open":"70.5","high":"70.87","low":"69.625","close":"70.5","volume":"31801"},{"date":"20100629","ticker":"NKE","open":"69.63","high":"69.67","low":"67.44","close":"68.17","volume":"58302"},{"date":"20100630","ticker":"NKE","open":"67.94","high":"69.14","low":"67.3","close":"67.55","volume":"46378"},{"date":"20100701","ticker":"NKE","open":"67.56","high":"68.5","low":"66.77","close":"68.07","volume":"51206"},{"date":"20100702","ticker":"NKE","open":"68.19","high":"68.94","low":"67.43","close":"67.86","volume":"29067"},{"date":"20100706","ticker":"NKE","open":"68.21","high":"69.17","low":"66.34","close":"67.21","volume":"42187"},{"date":"20100707","ticker":"NKE","open":"67.47","high":"68.59","low":"67.01","close":"68.56","volume":"42929"},{"date":"20100708","ticker":"NKE","open":"69.23","high":"70.48","low":"69.02","close":"70.28","volume":"44504"},{"date":"20100709","ticker":"NKE","open":"70.11","high":"70.21","low":"69.52","close":"70.15","volume":"27406"},{"date":"20100712","ticker":"NKE","open":"69.91","high":"70.47","low":"69.28","close":"69.81","volume":"22224"},{"date":"20100713","ticker":"NKE","open":"70.4","high":"70.92","low":"70.02","close":"70.47","volume":"30324"},{"date":"20100714","ticker":"NKE","open":"70.16","high":"70.6","low":"69.47","close":"70.54","volume":"29140"},{"date":"20100715","ticker":"NKE","open":"70.34","high":"70.8","low":"69.35","close":"70.65","volume":"35258"},{"date":"20100716","ticker":"NKE","open":"70.35","high":"70.66","low":"68.69","close":"68.96","volume":"34259"},{"date":"20100719","ticker":"NKE","open":"69.14","high":"69.47","low":"68.19","close":"68.61","volume":"23950"},{"date":"20100720","ticker":"NKE","open":"68.01","high":"70","low":"67.62","close":"69.84","volume":"37010"},{"date":"20100721","ticker":"NKE","open":"70.13","high":"71.07","low":"69.31","close":"69.65","volume":"39472"},{"date":"20100722","ticker":"NKE","open":"70.39","high":"72.12","low":"70.36","close":"71.56","volume":"33820"},{"date":"20100723","ticker":"NKE","open":"71.5","high":"73.16","low":"71.16","close":"72.74","volume":"28797"},{"date":"20100726","ticker":"NKE","open":"72.71","high":"73.95","low":"72.4826","close":"73.22","volume":"26229"},{"date":"20100727","ticker":"NKE","open":"73.7","high":"73.85","low":"72.84","close":"73.68","volume":"26031"},{"date":"20100728","ticker":"NKE","open":"73.64","high":"74.02","low":"72.87","close":"73.11","volume":"21141"},{"date":"20100729","ticker":"NKE","open":"73.65","high":"74.11","low":"72.68","close":"73.53","volume":"24161"},{"date":"20100730","ticker":"NKE","open":"72.69","high":"73.95","low":"72.64","close":"73.64","volume":"21757"},{"date":"20100802","ticker":"NKE","open":"74.7","high":"74.97","low":"73.94","close":"74.32","volume":"25670"},{"date":"20100803","ticker":"NKE","open":"74.2","high":"74.2","low":"72.85","close":"73.1","volume":"31809"},{"date":"20100804","ticker":"NKE","open":"73.18","high":"74.37","low":"73.13","close":"74","volume":"30394"},{"date":"20100805","ticker":"NKE","open":"73.42","high":"74.36","low":"73.3","close":"74.06","volume":"20164"},{"date":"20100806","ticker":"NKE","open":"73.42","high":"74.09","low":"72.78","close":"73.96","volume":"19247"},{"date":"20100809","ticker":"NKE","open":"74.14","high":"75","low":"73.88","close":"74.12","volume":"19734"},{"date":"20100810","ticker":"NKE","open":"73.42","high":"74.39","low":"72.8","close":"73.91","volume":"23466"},{"date":"20100811","ticker":"NKE","open":"72.77","high":"72.78","low":"71.48","close":"72.08","volume":"30380"},{"date":"20100812","ticker":"NKE","open":"70.99","high":"71.79","low":"70.7","close":"71.52","volume":"24380"},{"date":"20100813","ticker":"NKE","open":"71.41","high":"71.48","low":"70.48","close":"70.58","volume":"21986"},{"date":"20100816","ticker":"NKE","open":"70.11","high":"71.47","low":"69.77","close":"71.06","volume":"23814"},{"date":"20100817","ticker":"NKE","open":"71.75","high":"72.71","low":"71.47","close":"71.71","volume":"25309"},{"date":"20100819","ticker":"NKE","open":"71.81","high":"72.01","low":"70.56","close":"71.34","volume":"24702"},{"date":"20100820","ticker":"NKE","open":"70.73","high":"71.41","low":"70.49","close":"71.26","volume":"17879"}]